server/__init__.py
server/db_interface.py
server/descriptors.py
server/main.py
server/metacls.py
server/server.py
server/common/__init__.py
server/common/settings.py
server/log/__init__.py
server/log/server_log_config.py
moths_server-0.0.2.dist-info/METADATA
moths_server-0.0.2.dist-info/WHEEL
moths_server-0.0.2.dist-info/top_level.txt
moths_server-0.0.2.dist-info/RECORD
