Metadata-Version: 2.1
Name: moths-server
Version: 0.0.2
Summary: messenger_project_server
Home-page: UNKNOWN
Author: Fedor Kleshchev
Author-email: f.kleshev@gmail.com
License: UNKNOWN
Platform: UNKNOWN
Requires-Dist: PyQt5
Requires-Dist: sqlalchemy
Requires-Dist: threading
